naming/__init__.py
naming/base.py
naming-0.7.1.dist-info/LICENSE
naming-0.7.1.dist-info/METADATA
naming-0.7.1.dist-info/WHEEL
naming-0.7.1.dist-info/top_level.txt
naming-0.7.1.dist-info/RECORD
