Metadata-Version: 2.1
Name: naming
Version: 0.7.1
Summary: Object-oriented names for the digital era.
Home-page: https://github.com/chrizzFTD/naming
Author: Christian López Barrón
Author-email: chris.gfz@gmail.com
Keywords: name names naming convention configuration config cfg regex
Classifier: Programming Language :: Python :: 3.8
Classifier: Programming Language :: Python :: 3.9
Classifier: Programming Language :: Python :: 3.10
Classifier: Programming Language :: Python :: 3.11
Classifier: Programming Language :: Python :: 3.12
License-File: LICENSE
Provides-Extra: docs
Requires-Dist: sphinx ; extra == 'docs'
Requires-Dist: myst-parser ; extra == 'docs'
Requires-Dist: sphinx-toggleprompt ; extra == 'docs'
Requires-Dist: sphinx-copybutton ; extra == 'docs'
Requires-Dist: sphinx-togglebutton ; extra == 'docs'
Requires-Dist: sphinx-hoverxref ; extra == 'docs'
Requires-Dist: sphinx-autodoc-typehints ; extra == 'docs'
Requires-Dist: sphinx-rtd-theme ; extra == 'docs'
